coinoxr/__init__.py
coinoxr/client.py
coinoxr/convert.py
coinoxr/currency.py
coinoxr/error.py
coinoxr/historical.py
coinoxr/latest.py
coinoxr/ohlc.py
coinoxr/requestor.py
coinoxr/response.py
coinoxr/time_series.py
coinoxr/usage.py
coinoxr-0.0.1a0.dist-info/LICENSE
coinoxr-0.0.1a0.dist-info/METADATA
coinoxr-0.0.1a0.dist-info/WHEEL
coinoxr-0.0.1a0.dist-info/top_level.txt
coinoxr-0.0.1a0.dist-info/RECORD
