Metadata-Version: 2.1
Name: coinoxr
Version: 0.0.1a0
Summary: Python client for Open Exchange Rates
Home-page: UNKNOWN
Author: Luis Calado
Author-email: me@luiscalado.eu
License: MIT
Platform: UNKNOWN
Requires-Python: >=3.5
Requires-Dist: requests (>=2.20)
